kpdvdb/__init__.py
kpdvdb-0.6.3.dist-info/licenses/LICENSE
kpdvdb-0.6.3.dist-info/METADATA
kpdvdb-0.6.3.dist-info/WHEEL
kpdvdb-0.6.3.dist-info/top_level.txt
kpdvdb-0.6.3.dist-info/RECORD
