Metadata-Version: 2.4
Name: kpdvdb
Version: 0.6.3
Summary: KayPENTAX Disordered Voice Database Reader module
License: GPL-2.0 License
Project-URL: Repository, https://github.com/tikuma-lsuhsc/python-kpdvdb
Project-URL: Issues, https://github.com/tikuma-lsuhsc/python-kpdvdb/issues
Project-URL: Pull_Requests, https://github.com/tikuma-lsuhsc/python-kpdvdb/pulls
Keywords: multimedia
Classifier: Development Status :: 4 - Beta
Classifier: License :: OSI Approved :: GNU General Public License v2 (GPLv2)
Classifier: Topic :: Multimedia :: Sound/Audio
Classifier: Programming Language :: Python :: 3
Requires-Python: >=3.8
License-File: LICENSE
Requires-Dist: pandas
Requires-Dist: nspfile>=0.1.2
Dynamic: license-file
